WssPlugin_integration-1.1.1.dist-info/DESCRIPTION.rst
WssPlugin_integration-1.1.1.dist-info/METADATA
WssPlugin_integration-1.1.1.dist-info/RECORD
WssPlugin_integration-1.1.1.dist-info/WHEEL
WssPlugin_integration-1.1.1.dist-info/metadata.json
WssPlugin_integration-1.1.1.dist-info/top_level.txt
agent/__init__.py
agent/api/__init__.py
agent/api/dispatch/BaseRequest.py
agent/api/dispatch/CheckPoliciesRequest.py
agent/api/dispatch/CheckPoliciesResult.py
agent/api/dispatch/RequestType.py
agent/api/dispatch/ResultEnvelope.py
agent/api/dispatch/UpdateInventoryRequest.py
agent/api/dispatch/UpdateInventoryResult.py
agent/api/dispatch/__init__.py
agent/api/model/AgentProjectInfo.py
agent/api/model/Coordinates.py
agent/api/model/DependencyInfo.py
agent/api/model/PolicyCheckResourceNode.py
agent/api/model/RequestPolicyInfo.py
agent/api/model/ResourceInfo.py
agent/api/model/__init__.py
agent/client/WssServiceClient.py
agent/client/__init__.py
plugin/WssPythonPlugin.py
plugin/__init__.py
