Metadata-Version: 2.0
Name: WssPlugin-integration
Version: 1.1.1
Summary: Wss python pluging for creating/updating wss organization inventory
Home-page: UNKNOWN
Author: Yossi Weinberg
Author-email: yossi.weinberg@whitesourcesoftware.com
License: Apache 2.0
Platform: UNKNOWN
Requires-Dist: enum34 (==1.1.6)
Requires-Dist: jsonpickle (==0.9.4)
Requires-Dist: requests (==2.13.0)
